Metadata-Version: 2.4
Name: compressed-tensors
Version: 0.13.0
Summary: Library for utilization of compressed safetensors of neural network models
Home-page: https://github.com/vllm-project/compressed-tensors
Author: Neuralmagic, Inc.
Author-email: support@neuralmagic.com
License: Apache 2.0
License-File: LICENSE
Requires-Dist: torch>=1.7.0
Requires-Dist: transformers
Requires-Dist: pydantic>=2.0
Requires-Dist: loguru
Provides-Extra: dev
Requires-Dist: black==22.12.0; extra == "dev"
Requires-Dist: isort==5.8.0; extra == "dev"
Requires-Dist: wheel>=0.36.2; extra == "dev"
Requires-Dist: flake8>=3.8.3; extra == "dev"
Requires-Dist: pytest>=6.0.0; extra == "dev"
Requires-Dist: nbconvert>=7.16.3; extra == "dev"
Provides-Extra: accelerate
Requires-Dist: accelerate; extra == "accelerate"
Dynamic: author
Dynamic: author-email
Dynamic: description
Dynamic: description-content-type
Dynamic: home-page
Dynamic: license
Dynamic: license-file
Dynamic: provides-extra
Dynamic: requires-dist
Dynamic: summary
